hallmasterapi/__init__.py
hallmasterapi/hallmasterapi.py
HallmasterAPI-0.1.4.dist-info/LICENSE
HallmasterAPI-0.1.4.dist-info/METADATA
HallmasterAPI-0.1.4.dist-info/WHEEL
HallmasterAPI-0.1.4.dist-info/top_level.txt
HallmasterAPI-0.1.4.dist-info/RECORD
