Metadata-Version: 2.1
Name: HallmasterAPI
Version: 0.1.4
Summary: Python wrapper for the Hallmaster API
Author: Matthew Larby
Project-URL: Homepage, https://github.com/mattl1598/HallmasterAPI
Project-URL: Bug Tracker, https://github.com/mattl1598/HallmasterAPI/issues
Classifier: Programming Language :: Python :: 3
Classifier: License :: OSI Approved :: GNU General Public License v3 (GPLv3)
Classifier: Operating System :: OS Independent
Requires-Python: >=3.10
License-File: LICENSE
Requires-Dist: requests
Requires-Dist: beautifulsoup4
